ezqm/__init__.py
ezqm/ezcf.py
ezqm/ezcp.py
ezqm/ezgdb.py
ezqm/ezqm.py
ezqm/ezlib/__init__.py
ezqm/ezlib/printing.py
ezqm/ezlib/settings.py
ezqm/ezlib/utils.py
ezqm-1.0.5.dist-info/METADATA
ezqm-1.0.5.dist-info/WHEEL
ezqm-1.0.5.dist-info/entry_points.txt
ezqm-1.0.5.dist-info/top_level.txt
ezqm-1.0.5.dist-info/RECORD
