Metadata-Version: 2.1
Name: ezqm
Version: 1.0.5
Requires-Dist: pexpect
